infrablocks/invoke_terraform/example.py
infrablocks/invoke_terraform/py.typed
infrablocks_invoke_terraform-0.0.1.dist-info/LICENSE
infrablocks_invoke_terraform-0.0.1.dist-info/LICENSE.md
infrablocks_invoke_terraform-0.0.1.dist-info/METADATA
infrablocks_invoke_terraform-0.0.1.dist-info/WHEEL
infrablocks_invoke_terraform-0.0.1.dist-info/RECORD
