Metadata-Version: 2.1
Name: infrablocks.invoke_terraform
Version: 0.0.1
Summary: Provides invoke tasks to interact with terraform
License: MIT
Author: Toby Clemson
Author-email: tobyclemson@gmail.com
Requires-Python: >=3.13,<4.0
Classifier: License :: OSI Approved :: MIT License
Classifier: Programming Language :: Python :: 3
Requires-Dist: invoke (>=2.2.0,<3.0.0)
